DESCRIPTION.rst
MANIFEST.in
setup.cfg
setup.py
daemon/systemd/marcomanager.service
daemon/systemv/mbootstrapbackd
etc/marcobootstrap/scheduled.db
etc/marcobootstrap/backend/backend.cfg
etc/marcobootstrap/backend/secret
etc/marcobootstrap/backend/certs/app.crt
etc/marcobootstrap/backend/certs/app.csr
etc/marcobootstrap/backend/certs/app.key
etc/marcobootstrap/backend/certs/app.old.key
etc/marcobootstrap/backend/certs/minion.key
etc/marcobootstrap/backend/certs/minion.pem
etc/marcobootstrap/backend/certs/receiver.crt
etc/marcobootstrap/backend/certs/receiver.csr
etc/marcobootstrap/backend/certs/receiver.key
etc/marcobootstrap/backend/certs/receiver.old.key
marcobootstrap/__init__.py
marcobootstrap.backend.egg-info/PKG-INFO
marcobootstrap.backend.egg-info/SOURCES.txt
marcobootstrap.backend.egg-info/dependency_links.txt
marcobootstrap.backend.egg-info/entry_points.txt
marcobootstrap.backend.egg-info/namespace_packages.txt
marcobootstrap.backend.egg-info/not-zip-safe
marcobootstrap.backend.egg-info/requires.txt
marcobootstrap.backend.egg-info/top_level.txt
marcobootstrap/backend/__init__.py
marcobootstrap/backend/backend.py
marcobootstrap/backend/conf.py
marcobootstrap/backend/models.py
usr/lib/marcobootstrap/backend/static/css/bootcode.css
usr/lib/marcobootstrap/backend/static/css/bootstrap.min.css
usr/lib/marcobootstrap/backend/static/css/jquery.datetimepicker.css
usr/lib/marcobootstrap/backend/static/css/scheduled.css
usr/lib/marcobootstrap/backend/static/css/style.css
usr/lib/marcobootstrap/backend/static/fonts/glyphicons-halflings-regular.eot
usr/lib/marcobootstrap/backend/static/fonts/glyphicons-halflings-regular.svg
usr/lib/marcobootstrap/backend/static/fonts/glyphicons-halflings-regular.ttf
usr/lib/marcobootstrap/backend/static/fonts/glyphicons-halflings-regular.woff
usr/lib/marcobootstrap/backend/static/fonts/glyphicons-halflings-regular.woff2
usr/lib/marcobootstrap/backend/static/img/wait.gif
usr/lib/marcobootstrap/backend/static/js/bootcode.js
usr/lib/marcobootstrap/backend/static/js/bootstrap.min.js
usr/lib/marcobootstrap/backend/static/js/index.js
usr/lib/marcobootstrap/backend/static/js/jquery-ui.min.js
usr/lib/marcobootstrap/backend/static/js/jquery.datetimepicker.js
usr/lib/marcobootstrap/backend/static/js/jquery.min.js
usr/lib/marcobootstrap/backend/static/js/scheduled.js
usr/lib/marcobootstrap/backend/templates/403.jade
