Metadata-Version: 1.1
Name: marcobootstrap.backend
Version: 0.0.3
Summary: The marcobootstrap utility
Home-page: marcopolo.martinarroyo.net
Author: Diego Martín
Author-email: martinarroyo@usal.es
License: MIT
Keywords: pxe
Platform: UNKNOWN
Classifier: Development Status :: 3 - Alpha
Classifier: Topic :: System :: Boot
Classifier: Programming Language :: Python :: 2.7
Classifier: Programming Language :: Python :: 3.4
Classifier: Intended Audience :: System Administrators
Classifier: License :: OSI Approved :: Mozilla Public License 2.0 (MPL 2.0)
Classifier: Programming Language :: Python :: 2.7
Classifier: Programming Language :: Python :: 3.4
Classifier: Natural Language :: English
Provides: marcobootstrap.backend
